psmtemplate/__init__.py
psmtemplate/psmtemplate.py
psmtemplate/test.py
psmtemplate/static/ARIAL.ttf
psmtemplate/static/PSM Logo.jpg
psmtemplate/static/__init__.py
psmtemplate/static/matplotlibrc
psmtemplate-0.0.10.dist-info/LICENSE
psmtemplate-0.0.10.dist-info/METADATA
psmtemplate-0.0.10.dist-info/WHEEL
psmtemplate-0.0.10.dist-info/top_level.txt
psmtemplate-0.0.10.dist-info/RECORD
