Metadata-Version: 2.1
Name: psmtemplate
Version: 0.0.10
Summary: PSM Templates
Home-page: UNKNOWN
Author: Jianan Jiang
Author-email: jianan.jiang@psm.com.au
License: UNKNOWN
Platform: UNKNOWN
Classifier: Programming Language :: Python :: 3
Classifier: Operating System :: OS Independent
Requires-Python: >=3.6
Requires-Dist: reportlab
Requires-Dist: matplotlib
Requires-Dist: pdfrw
Requires-Dist: pillow
Requires-Dist: importlib-resources ; python_version < "3.7"
